{
    "current": {
        "fromDateTime": "2025-05-15T21:18:34.555Z",
        "indexes": [
            {
                "advice": "The air is great!",
                "color": "#6BC926",
                "description": "Great air here today!",
                "level": "VERY_LOW",
                "name": "AIRLY_CAQI",
                "value": 12.82
            }
        ],
        "standards": [
            {
                "averaging": "24h",
                "limit": 15.0,
                "name": "WHO",
                "percent": 51.26,
                "pollutant": "PM25"
            },
            {
                "averaging": "24h",
                "limit": 45.0,
                "name": "WHO",
                "percent": 23.31,
                "pollutant": "PM10"
            }
        ],
        "tillDateTime": "2025-05-15T22:18:34.555Z",
        "values": [
            {
                "name": "PM1",
                "value": 5.23
            },
            {
                "name": "PM25",
                "value": 7.69
            },
            {
                "name": "PM10",
                "value": 10.49
            },
            {
                "name": "PRESSURE",
                "value": 1011.44
            },
            {
                "name": "HUMIDITY",
                "value": 92.13
            },
            {
                "name": "TEMPERATURE",
                "value": 3.76
            },
            {
                "name": "WIND_SPEED",
                "value": 10.58
            },
            {
                "name": "WIND_BEARING",
                "value": 281.0
            }
        ]
    },
    "forecast": [
        {
            "fromDateTime": "2025-05-15T22:00:00.000Z",
            "indexes": [
                {
                    "advice": "Breathe deeply!",
                    "color": "#6BC926",
                    "description": "Great air here today!",
                    "level": "VERY_LOW",
                    "name": "AIRLY_CAQI",
                    "value": 13.22
                }
            ],
            "standards": [
                {
                    "averaging": "24h",
                    "limit": 15.0,
                    "name": "WHO",
                    "percent": 52.85,
                    "pollutant": "PM25"
                },
                {
                    "averaging": "24h",
                    "limit": 45.0,
                    "name": "WHO",
                    "percent": 19.31,
                    "pollutant": "PM10"
                }
            ],
            "tillDateTime": "2025-05-15T23:00:00.000Z",
            "values": [
                {
                    "name": "PM25",
                    "value": 7.93
                },
                {
                    "name": "PM10",
                    "value": 8.69
                }
            ]
        },
        {
            "fromDateTime": "2025-05-15T23:00:00.000Z",
            "indexes": [
                {
                    "advice": "The air is grand today. ;)",
                    "color": "#6BC926",
                    "description": "Great air here today!",
                    "level": "VERY_LOW",
                    "name": "AIRLY_CAQI",
                    "value": 13.29
                }
            ],
            "standards": [
                {
                    "averaging": "24h",
                    "limit": 15.0,
                    "name": "WHO",
                    "percent": 53.16,
                    "pollutant": "PM25"
                },
                {
                    "averaging": "24h",
                    "limit": 45.0,
                    "name": "WHO",
                    "percent": 19.98,
                    "pollutant": "PM10"
                }
            ],
            "tillDateTime": "2025-05-16T00:00:00.000Z",
            "values": [
                {
                    "name": "PM25",
                    "value": 7.97
                },
                {
                    "name": "PM10",
                    "value": 8.99
                }
            ]
        },
        {
            "fromDateTime": "2025-05-16T00:00:00.000Z",
            "indexes": [
                {
                    "advice": "Dear me, how wonderful!",
                    "color": "#6BC926",
                    "description": "Great air here today!",
                    "level": "VERY_LOW",
                    "name": "AIRLY_CAQI",
                    "value": 12.98
                }
            ],
            "standards": [
                {
                    "averaging": "24h",
                    "limit": 15.0,
                    "name": "WHO",
                    "percent": 51.89,
                    "pollutant": "PM25"
                },
                {
                    "averaging": "24h",
                    "limit": 45.0,
                    "name": "WHO",
                    "percent": 21.12,
                    "pollutant": "PM10"
                }
            ],
            "tillDateTime": "2025-05-16T01:00:00.000Z",
            "values": [
                {
                    "name": "PM25",
                    "value": 7.78
                },
                {
                    "name": "PM10",
                    "value": 9.51
                }
            ]
        },
        {
            "fromDateTime": "2025-05-16T01:00:00.000Z",
            "indexes": [
                {
                    "advice": "Green equals clean!",
                    "color": "#6BC926",
                    "description": "Great air here today!",
                    "level": "VERY_LOW",
                    "name": "AIRLY_CAQI",
                    "value": 13.1
                }
            ],
            "standards": [
                {
                    "averaging": "24h",
                    "limit": 15.0,
                    "name": "WHO",
                    "percent": 52.4,
                    "pollutant": "PM25"
                },
                {
                    "averaging": "24h",
                    "limit": 45.0,
                    "name": "WHO",
                    "percent": 20.48,
                    "pollutant": "PM10"
                }
            ],
            "tillDateTime": "2025-05-16T02:00:00.000Z",
            "values": [
                {
                    "name": "PM25",
                    "value": 7.86
                },
                {
                    "name": "PM10",
                    "value": 9.22
                }
            ]
        },
        {
            "fromDateTime": "2025-05-16T02:00:00.000Z",
            "indexes": [
                {
                    "advice": "Dear me, how wonderful!",
                    "color": "#6BC926",
                    "description": "Great air here today!",
                    "level": "VERY_LOW",
                    "name": "AIRLY_CAQI",
                    "value": 12.72
                }
            ],
            "standards": [
                {
                    "averaging": "24h",
                    "limit": 15.0,
                    "name": "WHO",
                    "percent": 50.85,
                    "pollutant": "PM25"
                },
                {
                    "averaging": "24h",
                    "limit": 45.0,
                    "name": "WHO",
                    "percent": 20.95,
                    "pollutant": "PM10"
                }
            ],
            "tillDateTime": "2025-05-16T03:00:00.000Z",
            "values": [
                {
                    "name": "PM25",
                    "value": 7.63
                },
                {
                    "name": "PM10",
                    "value": 9.43
                }
            ]
        },
        {
            "fromDateTime": "2025-05-16T03:00:00.000Z",
            "indexes": [
                {
                    "advice": "It couldn't be better ;)",
                    "color": "#6BC926",
                    "description": "Great air here today!",
                    "level": "VERY_LOW",
                    "name": "AIRLY_CAQI",
                    "value": 10.94
                }
            ],
            "standards": [
                {
                    "averaging": "24h",
                    "limit": 15.0,
                    "name": "WHO",
                    "percent": 43.76,
                    "pollutant": "PM25"
                },
                {
                    "averaging": "24h",
                    "limit": 45.0,
                    "name": "WHO",
                    "percent": 20.48,
                    "pollutant": "PM10"
                }
            ],
            "tillDateTime": "2025-05-16T04:00:00.000Z",
            "values": [
                {
                    "name": "PM25",
                    "value": 6.56
                },
                {
                    "name": "PM10",
                    "value": 9.22
                }
            ]
        },
        {
            "fromDateTime": "2025-05-16T04:00:00.000Z",
            "indexes": [
                {
                    "advice": "Breathe deeply!",
                    "color": "#6BC926",
                    "description": "Great air here today!",
                    "level": "VERY_LOW",
                    "name": "AIRLY_CAQI",
                    "value": 11.69
                }
            ],
            "standards": [
                {
                    "averaging": "24h",
                    "limit": 15.0,
                    "name": "WHO",
                    "percent": 46.73,
                    "pollutant": "PM25"
                },
                {
                    "averaging": "24h",
                    "limit": 45.0,
                    "name": "WHO",
                    "percent": 20.64,
                    "pollutant": "PM10"
                }
            ],
            "tillDateTime": "2025-05-16T05:00:00.000Z",
            "values": [
                {
                    "name": "PM25",
                    "value": 7.01
                },
                {
                    "name": "PM10",
                    "value": 9.29
                }
            ]
        },
        {
            "fromDateTime": "2025-05-16T05:00:00.000Z",
            "indexes": [
                {
                    "advice": "Breathe to fill your lungs!",
                    "color": "#6BC926",
                    "description": "Great air here today!",
                    "level": "VERY_LOW",
                    "name": "AIRLY_CAQI",
                    "value": 11.85
                }
            ],
            "standards": [
                {
                    "averaging": "24h",
                    "limit": 15.0,
                    "name": "WHO",
                    "percent": 47.36,
                    "pollutant": "PM25"
                },
                {
                    "averaging": "24h",
                    "limit": 45.0,
                    "name": "WHO",
                    "percent": 19.53,
                    "pollutant": "PM10"
                }
            ],
            "tillDateTime": "2025-05-16T06:00:00.000Z",
            "values": [
                {
                    "name": "PM25",
                    "value": 7.1
                },
                {
                    "name": "PM10",
                    "value": 8.79
                }
            ]
        },
        {
            "fromDateTime": "2025-05-16T06:00:00.000Z",
            "indexes": [
                {
                    "advice": "It couldn't be better ;)",
                    "color": "#6BC926",
                    "description": "Great air here today!",
                    "level": "VERY_LOW",
                    "name": "AIRLY_CAQI",
                    "value": 11.89
                }
            ],
            "standards": [
                {
                    "averaging": "24h",
                    "limit": 15.0,
                    "name": "WHO",
                    "percent": 47.55,
                    "pollutant": "PM25"
                },
                {
                    "averaging": "24h",
                    "limit": 45.0,
                    "name": "WHO",
                    "percent": 18.51,
                    "pollutant": "PM10"
                }
            ],
            "tillDateTime": "2025-05-16T07:00:00.000Z",
            "values": [
                {
                    "name": "PM25",
                    "value": 7.13
                },
                {
                    "name": "PM10",
                    "value": 8.33
                }
            ]
        },
        {
            "fromDateTime": "2025-05-16T07:00:00.000Z",
            "indexes": [
                {
                    "advice": "Great air!",
                    "color": "#6BC926",
                    "description": "Great air here today!",
                    "level": "VERY_LOW",
                    "name": "AIRLY_CAQI",
                    "value": 11.97
                }
            ],
            "standards": [
                {
                    "averaging": "24h",
                    "limit": 15.0,
                    "name": "WHO",
                    "percent": 47.87,
                    "pollutant": "PM25"
                },
                {
                    "averaging": "24h",
                    "limit": 45.0,
                    "name": "WHO",
                    "percent": 17.34,
                    "pollutant": "PM10"
                }
            ],
            "tillDateTime": "2025-05-16T08:00:00.000Z",
            "values": [
                {
                    "name": "PM25",
                    "value": 7.18
                },
                {
                    "name": "PM10",
                    "value": 7.8
                }
            ]
        },
        {
            "fromDateTime": "2025-05-16T08:00:00.000Z",
            "indexes": [
                {
                    "advice": "The air is grand today. ;)",
                    "color": "#6BC926",
                    "description": "Great air here today!",
                    "level": "VERY_LOW",
                    "name": "AIRLY_CAQI",
                    "value": 11.83
                }
            ],
            "standards": [
                {
                    "averaging": "24h",
                    "limit": 15.0,
                    "name": "WHO",
                    "percent": 47.32,
                    "pollutant": "PM25"
                },
                {
                    "averaging": "24h",
                    "limit": 45.0,
                    "name": "WHO",
                    "percent": 16.87,
                    "pollutant": "PM10"
                }
            ],
            "tillDateTime": "2025-05-16T09:00:00.000Z",
            "values": [
                {
                    "name": "PM25",
                    "value": 7.1
                },
                {
                    "name": "PM10",
                    "value": 7.59
                }
            ]
        },
        {
            "fromDateTime": "2025-05-16T09:00:00.000Z",
            "indexes": [
                {
                    "advice": "Green equals clean!",
                    "color": "#6BC926",
                    "description": "Great air here today!",
                    "level": "VERY_LOW",
                    "name": "AIRLY_CAQI",
                    "value": 11.07
                }
            ],
            "standards": [
                {
                    "averaging": "24h",
                    "limit": 15.0,
                    "name": "WHO",
                    "percent": 44.25,
                    "pollutant": "PM25"
                },
                {
                    "averaging": "24h",
                    "limit": 45.0,
                    "name": "WHO",
                    "percent": 16.82,
                    "pollutant": "PM10"
                }
            ],
            "tillDateTime": "2025-05-16T10:00:00.000Z",
            "values": [
                {
                    "name": "PM25",
                    "value": 6.64
                },
                {
                    "name": "PM10",
                    "value": 7.57
                }
            ]
        },
        {
            "fromDateTime": "2025-05-16T10:00:00.000Z",
            "indexes": [
                {
                    "advice": "Breathe as much as you can!",
                    "color": "#6BC926",
                    "description": "Great air here today!",
                    "level": "VERY_LOW",
                    "name": "AIRLY_CAQI",
                    "value": 9.38
                }
            ],
            "standards": [
                {
                    "averaging": "24h",
                    "limit": 15.0,
                    "name": "WHO",
                    "percent": 37.49,
                    "pollutant": "PM25"
                },
                {
                    "averaging": "24h",
                    "limit": 45.0,
                    "name": "WHO",
                    "percent": 16.22,
                    "pollutant": "PM10"
                }
            ],
            "tillDateTime": "2025-05-16T11:00:00.000Z",
            "values": [
                {
                    "name": "PM25",
                    "value": 5.62
                },
                {
                    "name": "PM10",
                    "value": 7.3
                }
            ]
        },
        {
            "fromDateTime": "2025-05-16T11:00:00.000Z",
            "indexes": [
                {
                    "advice": "It couldn't be better ;)",
                    "color": "#6BC926",
                    "description": "Great air here today!",
                    "level": "VERY_LOW",
                    "name": "AIRLY_CAQI",
                    "value": 7.92
                }
            ],
            "standards": [
                {
                    "averaging": "24h",
                    "limit": 15.0,
                    "name": "WHO",
                    "percent": 30.92,
                    "pollutant": "PM25"
                },
                {
                    "averaging": "24h",
                    "limit": 45.0,
                    "name": "WHO",
                    "percent": 17.6,
                    "pollutant": "PM10"
                }
            ],
            "tillDateTime": "2025-05-16T12:00:00.000Z",
            "values": [
                {
                    "name": "PM25",
                    "value": 4.64
                },
                {
                    "name": "PM10",
                    "value": 7.92
                }
            ]
        },
        {
            "fromDateTime": "2025-05-16T12:00:00.000Z",
            "indexes": [
                {
                    "advice": "Breathe as much as you can!",
                    "color": "#6BC926",
                    "description": "Great air here today!",
                    "level": "VERY_LOW",
                    "name": "AIRLY_CAQI",
                    "value": 8.37
                }
            ],
            "standards": [
                {
                    "averaging": "24h",
                    "limit": 15.0,
                    "name": "WHO",
                    "percent": 26.56,
                    "pollutant": "PM25"
                },
                {
                    "averaging": "24h",
                    "limit": 45.0,
                    "name": "WHO",
                    "percent": 18.58,
                    "pollutant": "PM10"
                }
            ],
            "tillDateTime": "2025-05-16T13:00:00.000Z",
            "values": [
                {
                    "name": "PM25",
                    "value": 3.98
                },
                {
                    "name": "PM10",
                    "value": 8.36
                }
            ]
        },
        {
            "fromDateTime": "2025-05-16T13:00:00.000Z",
            "indexes": [
                {
                    "advice": "Green equals clean!",
                    "color": "#6BC926",
                    "description": "Great air here today!",
                    "level": "VERY_LOW",
                    "name": "AIRLY_CAQI",
                    "value": 8.55
                }
            ],
            "standards": [
                {
                    "averaging": "24h",
                    "limit": 15.0,
                    "name": "WHO",
                    "percent": 23.13,
                    "pollutant": "PM25"
                },
                {
                    "averaging": "24h",
                    "limit": 45.0,
                    "name": "WHO",
                    "percent": 18.98,
                    "pollutant": "PM10"
                }
            ],
            "tillDateTime": "2025-05-16T14:00:00.000Z",
            "values": [
                {
                    "name": "PM25",
                    "value": 3.47
                },
                {
                    "name": "PM10",
                    "value": 8.54
                }
            ]
        },
        {
            "fromDateTime": "2025-05-16T14:00:00.000Z",
            "indexes": [
                {
                    "advice": "Green equals clean!",
                    "color": "#6BC926",
                    "description": "Great air here today!",
                    "level": "VERY_LOW",
                    "name": "AIRLY_CAQI",
                    "value": 8.69
                }
            ],
            "standards": [
                {
                    "averaging": "24h",
                    "limit": 15.0,
                    "name": "WHO",
                    "percent": 22.02,
                    "pollutant": "PM25"
                },
                {
                    "averaging": "24h",
                    "limit": 45.0,
                    "name": "WHO",
                    "percent": 19.3,
                    "pollutant": "PM10"
                }
            ],
            "tillDateTime": "2025-05-16T15:00:00.000Z",
            "values": [
                {
                    "name": "PM25",
                    "value": 3.3
                },
                {
                    "name": "PM10",
                    "value": 8.68
                }
            ]
        },
        {
            "fromDateTime": "2025-05-16T15:00:00.000Z",
            "indexes": [
                {
                    "advice": "Enjoy life!",
                    "color": "#6BC926",
                    "description": "Great air here today!",
                    "level": "VERY_LOW",
                    "name": "AIRLY_CAQI",
                    "value": 9.83
                }
            ],
            "standards": [
                {
                    "averaging": "24h",
                    "limit": 15.0,
                    "name": "WHO",
                    "percent": 22.89,
                    "pollutant": "PM25"
                },
                {
                    "averaging": "24h",
                    "limit": 45.0,
                    "name": "WHO",
                    "percent": 21.84,
                    "pollutant": "PM10"
                }
            ],
            "tillDateTime": "2025-05-16T16:00:00.000Z",
            "values": [
                {
                    "name": "PM25",
                    "value": 3.43
                },
                {
                    "name": "PM10",
                    "value": 9.83
                }
            ]
        },
        {
            "fromDateTime": "2025-05-16T16:00:00.000Z",
            "indexes": [
                {
                    "advice": "Dear me, how wonderful!",
                    "color": "#6BC926",
                    "description": "Great air here today!",
                    "level": "VERY_LOW",
                    "name": "AIRLY_CAQI",
                    "value": 12.64
                }
            ],
            "standards": [
                {
                    "averaging": "24h",
                    "limit": 15.0,
                    "name": "WHO",
                    "percent": 28.2,
                    "pollutant": "PM25"
                },
                {
                    "averaging": "24h",
                    "limit": 45.0,
                    "name": "WHO",
                    "percent": 28.08,
                    "pollutant": "PM10"
                }
            ],
            "tillDateTime": "2025-05-16T17:00:00.000Z",
            "values": [
                {
                    "name": "PM25",
                    "value": 4.23
                },
                {
                    "name": "PM10",
                    "value": 12.64
                }
            ]
        },
        {
            "fromDateTime": "2025-05-16T17:00:00.000Z",
            "indexes": [
                {
                    "advice": "The air is grand today. ;)",
                    "color": "#6BC926",
                    "description": "Great air here today!",
                    "level": "VERY_LOW",
                    "name": "AIRLY_CAQI",
                    "value": 15.83
                }
            ],
            "standards": [
                {
                    "averaging": "24h",
                    "limit": 15.0,
                    "name": "WHO",
                    "percent": 40.33,
                    "pollutant": "PM25"
                },
                {
                    "averaging": "24h",
                    "limit": 45.0,
                    "name": "WHO",
                    "percent": 35.17,
                    "pollutant": "PM10"
                }
            ],
            "tillDateTime": "2025-05-16T18:00:00.000Z",
            "values": [
                {
                    "name": "PM25",
                    "value": 6.05
                },
                {
                    "name": "PM10",
                    "value": 15.82
                }
            ]
        },
        {
            "fromDateTime": "2025-05-16T18:00:00.000Z",
            "indexes": [
                {
                    "advice": "Breathe deeply!",
                    "color": "#6BC926",
                    "description": "Great air here today!",
                    "level": "VERY_LOW",
                    "name": "AIRLY_CAQI",
                    "value": 18.65
                }
            ],
            "standards": [
                {
                    "averaging": "24h",
                    "limit": 15.0,
                    "name": "WHO",
                    "percent": 55.93,
                    "pollutant": "PM25"
                },
                {
                    "averaging": "24h",
                    "limit": 45.0,
                    "name": "WHO",
                    "percent": 41.44,
                    "pollutant": "PM10"
                }
            ],
            "tillDateTime": "2025-05-16T19:00:00.000Z",
            "values": [
                {
                    "name": "PM25",
                    "value": 8.39
                },
                {
                    "name": "PM10",
                    "value": 18.65
                }
            ]
        },
        {
            "fromDateTime": "2025-05-16T19:00:00.000Z",
            "indexes": [
                {
                    "advice": "Catch your breath!",
                    "color": "#6BC926",
                    "description": "Great air here today!",
                    "level": "VERY_LOW",
                    "name": "AIRLY_CAQI",
                    "value": 20.26
                }
            ],
            "standards": [
                {
                    "averaging": "24h",
                    "limit": 15.0,
                    "name": "WHO",
                    "percent": 67.01,
                    "pollutant": "PM25"
                },
                {
                    "averaging": "24h",
                    "limit": 45.0,
                    "name": "WHO",
                    "percent": 45.0,
                    "pollutant": "PM10"
                }
            ],
            "tillDateTime": "2025-05-16T20:00:00.000Z",
            "values": [
                {
                    "name": "PM25",
                    "value": 10.05
                },
                {
                    "name": "PM10",
                    "value": 20.25
                }
            ]
        },
        {
            "fromDateTime": "2025-05-16T20:00:00.000Z",
            "indexes": [
                {
                    "advice": "It couldn't be better ;)",
                    "color": "#6BC926",
                    "description": "Great air here today!",
                    "level": "VERY_LOW",
                    "name": "AIRLY_CAQI",
                    "value": 21.37
                }
            ],
            "standards": [
                {
                    "averaging": "24h",
                    "limit": 15.0,
                    "name": "WHO",
                    "percent": 73.96,
                    "pollutant": "PM25"
                },
                {
                    "averaging": "24h",
                    "limit": 45.0,
                    "name": "WHO",
                    "percent": 47.48,
                    "pollutant": "PM10"
                }
            ],
            "tillDateTime": "2025-05-16T21:00:00.000Z",
            "values": [
                {
                    "name": "PM25",
                    "value": 11.09
                },
                {
                    "name": "PM10",
                    "value": 21.36
                }
            ]
        },
        {
            "fromDateTime": "2025-05-16T21:00:00.000Z",
            "indexes": [
                {
                    "advice": "Breathe deep! The air is clean!",
                    "color": "#6BC926",
                    "description": "Great air here today!",
                    "level": "VERY_LOW",
                    "name": "AIRLY_CAQI",
                    "value": 20.58
                }
            ],
            "standards": [
                {
                    "averaging": "24h",
                    "limit": 15.0,
                    "name": "WHO",
                    "percent": 78.19,
                    "pollutant": "PM25"
                },
                {
                    "averaging": "24h",
                    "limit": 45.0,
                    "name": "WHO",
                    "percent": 45.71,
                    "pollutant": "PM10"
                }
            ],
            "tillDateTime": "2025-05-16T22:00:00.000Z",
            "values": [
                {
                    "name": "PM25",
                    "value": 11.73
                },
                {
                    "name": "PM10",
                    "value": 20.57
                }
            ]
        }
    ],
    "history": [
        {
            "fromDateTime": "2025-05-14T22:00:00.000Z",
            "indexes": [
                {
                    "advice": "Breathe to fill your lungs!",
                    "color": "#6BC926",
                    "description": "Great air here today!",
                    "level": "VERY_LOW",
                    "name": "AIRLY_CAQI",
                    "value": 15.59
                }
            ],
            "standards": [
                {
                    "averaging": "24h",
                    "limit": 15.0,
                    "name": "WHO",
                    "percent": 62.34,
                    "pollutant": "PM25"
                },
                {
                    "averaging": "24h",
                    "limit": 45.0,
                    "name": "WHO",
                    "percent": 27.12,
                    "pollutant": "PM10"
                }
            ],
            "tillDateTime": "2025-05-14T23:00:00.000Z",
            "values": [
                {
                    "name": "PM1",
                    "value": 6.76
                },
                {
                    "name": "PM25",
                    "value": 9.35
                },
                {
                    "name": "PM10",
                    "value": 12.2
                },
                {
                    "name": "PRESSURE",
                    "value": 1004.31
                },
                {
                    "name": "HUMIDITY",
                    "value": 67.67
                },
                {
                    "name": "TEMPERATURE",
                    "value": 12.18
                },
                {
                    "name": "WIND_SPEED",
                    "value": 10.54
                },
                {
                    "name": "WIND_BEARING",
                    "value": 258.28
                }
            ]
        },
        {
            "fromDateTime": "2025-05-14T23:00:00.000Z",
            "indexes": [
                {
                    "advice": "Breathe to fill your lungs!",
                    "color": "#6BC926",
                    "description": "Great air here today!",
                    "level": "VERY_LOW",
                    "name": "AIRLY_CAQI",
                    "value": 15.61
                }
            ],
            "standards": [
                {
                    "averaging": "24h",
                    "limit": 15.0,
                    "name": "WHO",
                    "percent": 62.42,
                    "pollutant": "PM25"
                },
                {
                    "averaging": "24h",
                    "limit": 45.0,
                    "name": "WHO",
                    "percent": 27.73,
                    "pollutant": "PM10"
                }
            ],
            "tillDateTime": "2025-05-15T00:00:00.000Z",
            "values": [
                {
                    "name": "PM1",
                    "value": 6.95
                },
                {
                    "name": "PM25",
                    "value": 9.36
                },
                {
                    "name": "PM10",
                    "value": 12.48
                },
                {
                    "name": "PRESSURE",
                    "value": 1003.78
                },
                {
                    "name": "HUMIDITY",
                    "value": 71.52
                },
                {
                    "name": "TEMPERATURE",
                    "value": 11.61
                },
                {
                    "name": "WIND_SPEED",
                    "value": 8.82
                },
                {
                    "name": "WIND_BEARING",
                    "value": 262.07
                }
            ]
        },
        {
            "fromDateTime": "2025-05-15T00:00:00.000Z",
            "indexes": [
                {
                    "advice": "It couldn't be better ;)",
                    "color": "#6BC926",
                    "description": "Great air here today!",
                    "level": "VERY_LOW",
                    "name": "AIRLY_CAQI",
                    "value": 12.02
                }
            ],
            "standards": [
                {
                    "averaging": "24h",
                    "limit": 15.0,
                    "name": "WHO",
                    "percent": 48.06,
                    "pollutant": "PM25"
                },
                {
                    "averaging": "24h",
                    "limit": 45.0,
                    "name": "WHO",
                    "percent": 21.06,
                    "pollutant": "PM10"
                }
            ],
            "tillDateTime": "2025-05-15T01:00:00.000Z",
            "values": [
                {
                    "name": "PM1",
                    "value": 5.26
                },
                {
                    "name": "PM25",
                    "value": 7.21
                },
                {
                    "name": "PM10",
                    "value": 9.48
                },
                {
                    "name": "PRESSURE",
                    "value": 1003.16
                },
                {
                    "name": "HUMIDITY",
                    "value": 74.0
                },
                {
                    "name": "TEMPERATURE",
                    "value": 11.31
                },
                {
                    "name": "WIND_SPEED",
                    "value": 7.38
                },
                {
                    "name": "WIND_BEARING",
                    "value": 263.84
                }
            ]
        },
        {
            "fromDateTime": "2025-05-15T01:00:00.000Z",
            "indexes": [
                {
                    "advice": "Dear me, how wonderful!",
                    "color": "#6BC926",
                    "description": "Great air here today!",
                    "level": "VERY_LOW",
                    "name": "AIRLY_CAQI",
                    "value": 13.1
                }
            ],
            "standards": [
                {
                    "averaging": "24h",
                    "limit": 15.0,
                    "name": "WHO",
                    "percent": 52.37,
                    "pollutant": "PM25"
                },
                {
                    "averaging": "24h",
                    "limit": 45.0,
                    "name": "WHO",
                    "percent": 22.7,
                    "pollutant": "PM10"
                }
            ],
            "tillDateTime": "2025-05-15T02:00:00.000Z",
            "values": [
                {
                    "name": "PM1",
                    "value": 5.68
                },
                {
                    "name": "PM25",
                    "value": 7.85
                },
                {
                    "name": "PM10",
                    "value": 10.21
                },
                {
                    "name": "PRESSURE",
                    "value": 1002.65
                },
                {
                    "name": "HUMIDITY",
                    "value": 77.0
                },
                {
                    "name": "TEMPERATURE",
                    "value": 10.53
                },
                {
                    "name": "WIND_SPEED",
                    "value": 6.82
                },
                {
                    "name": "WIND_BEARING",
                    "value": 275.08
                }
            ]
        },
        {
            "fromDateTime": "2025-05-15T02:00:00.000Z",
            "indexes": [
                {
                    "advice": "It couldn't be better ;)",
                    "color": "#6BC926",
                    "description": "Great air here today!",
                    "level": "VERY_LOW",
                    "name": "AIRLY_CAQI",
                    "value": 12.91
                }
            ],
            "standards": [
                {
                    "averaging": "24h",
                    "limit": 15.0,
                    "name": "WHO",
                    "percent": 51.6,
                    "pollutant": "PM25"
                },
                {
                    "averaging": "24h",
                    "limit": 45.0,
                    "name": "WHO",
                    "percent": 22.26,
                    "pollutant": "PM10"
                }
            ],
            "tillDateTime": "2025-05-15T03:00:00.000Z",
            "values": [
                {
                    "name": "PM1",
                    "value": 5.58
                },
                {
                    "name": "PM25",
                    "value": 7.74
                },
                {
                    "name": "PM10",
                    "value": 10.02
                },
                {
                    "name": "PRESSURE",
                    "value": 1001.99
                },
                {
                    "name": "HUMIDITY",
                    "value": 79.75
                },
                {
                    "name": "TEMPERATURE",
                    "value": 10.17
                },
                {
                    "name": "WIND_SPEED",
                    "value": 7.42
                },
                {
                    "name": "WIND_BEARING",
                    "value": 286.0
                }
            ]
        },
        {
            "fromDateTime": "2025-05-15T03:00:00.000Z",
            "indexes": [
                {
                    "advice": "Perfect air for exercising! Go for it!",
                    "color": "#6BC926",
                    "description": "Great air here today!",
                    "level": "VERY_LOW",
                    "name": "AIRLY_CAQI",
                    "value": 10.2
                }
            ],
            "standards": [
                {
                    "averaging": "24h",
                    "limit": 15.0,
                    "name": "WHO",
                    "percent": 40.78,
                    "pollutant": "PM25"
                },
                {
                    "averaging": "24h",
                    "limit": 45.0,
                    "name": "WHO",
                    "percent": 17.59,
                    "pollutant": "PM10"
                }
            ],
            "tillDateTime": "2025-05-15T04:00:00.000Z",
            "values": [
                {
                    "name": "PM1",
                    "value": 4.46
                },
                {
                    "name": "PM25",
                    "value": 6.12
                },
                {
                    "name": "PM10",
                    "value": 7.92
                },
                {
                    "name": "PRESSURE",
                    "value": 1002.48
                },
                {
                    "name": "HUMIDITY",
                    "value": 86.5
                },
                {
                    "name": "TEMPERATURE",
                    "value": 9.14
                },
                {
                    "name": "WIND_SPEED",
                    "value": 9.35
                },
                {
                    "name": "WIND_BEARING",
                    "value": 315.0
                }
            ]
        },
        {
            "fromDateTime": "2025-05-15T04:00:00.000Z",
            "indexes": [
                {
                    "advice": "Dear me, how wonderful!",
                    "color": "#6BC926",
                    "description": "Great air here today!",
                    "level": "VERY_LOW",
                    "name": "AIRLY_CAQI",
                    "value": 3.03
                }
            ],
            "standards": [
                {
                    "averaging": "24h",
                    "limit": 15.0,
                    "name": "WHO",
                    "percent": 12.09,
                    "pollutant": "PM25"
                },
                {
                    "averaging": "24h",
                    "limit": 45.0,
                    "name": "WHO",
                    "percent": 5.55,
                    "pollutant": "PM10"
                }
            ],
            "tillDateTime": "2025-05-15T05:00:00.000Z",
            "values": [
                {
                    "name": "PM1",
                    "value": 1.1
                },
                {
                    "name": "PM25",
                    "value": 1.81
                },
                {
                    "name": "PM10",
                    "value": 2.5
                },
                {
                    "name": "PRESSURE",
                    "value": 1003.57
                },
                {
                    "name": "HUMIDITY",
                    "value": 89.31
                },
                {
                    "name": "TEMPERATURE",
                    "value": 7.29
                },
                {
                    "name": "WIND_SPEED",
                    "value": 12.84
                },
                {
                    "name": "WIND_BEARING",
                    "value": 345.71
                }
            ]
        },
        {
            "fromDateTime": "2025-05-15T05:00:00.000Z",
            "indexes": [
                {
                    "advice": "It couldn't be better ;)",
                    "color": "#6BC926",
                    "description": "Great air here today!",
                    "level": "VERY_LOW",
                    "name": "AIRLY_CAQI",
                    "value": 2.19
                }
            ],
            "standards": [
                {
                    "averaging": "24h",
                    "limit": 15.0,
                    "name": "WHO",
                    "percent": 8.73,
                    "pollutant": "PM25"
                },
                {
                    "averaging": "24h",
                    "limit": 45.0,
                    "name": "WHO",
                    "percent": 4.18,
                    "pollutant": "PM10"
                }
            ],
            "tillDateTime": "2025-05-15T06:00:00.000Z",
            "values": [
                {
                    "name": "PM1",
                    "value": 0.75
                },
                {
                    "name": "PM25",
                    "value": 1.31
                },
                {
                    "name": "PM10",
                    "value": 1.88
                },
                {
                    "name": "PRESSURE",
                    "value": 1004.15
                },
                {
                    "name": "HUMIDITY",
                    "value": 90.81
                },
                {
                    "name": "TEMPERATURE",
                    "value": 5.48
                },
                {
                    "name": "WIND_SPEED",
                    "value": 17.52
                },
                {
                    "name": "WIND_BEARING",
                    "value": 3.92
                }
            ]
        },
        {
            "fromDateTime": "2025-05-15T06:00:00.000Z",
            "indexes": [
                {
                    "advice": "Breathe deep! The air is clean!",
                    "color": "#6BC926",
                    "description": "Great air here today!",
                    "level": "VERY_LOW",
                    "name": "AIRLY_CAQI",
                    "value": 1.59
                }
            ],
            "standards": [
                {
                    "averaging": "24h",
                    "limit": 15.0,
                    "name": "WHO",
                    "percent": 6.34,
                    "pollutant": "PM25"
                },
                {
                    "averaging": "24h",
                    "limit": 45.0,
                    "name": "WHO",
                    "percent": 2.85,
                    "pollutant": "PM10"
                }
            ],
            "tillDateTime": "2025-05-15T07:00:00.000Z",
            "values": [
                {
                    "name": "PM1",
                    "value": 0.64
                },
                {
                    "name": "PM25",
                    "value": 0.95
                },
                {
                    "name": "PM10",
                    "value": 1.28
                },
                {
                    "name": "PRESSURE",
                    "value": 1005.71
                },
                {
                    "name": "HUMIDITY",
                    "value": 92.69
                },
                {
                    "name": "TEMPERATURE",
                    "value": 3.74
                },
                {
                    "name": "WIND_SPEED",
                    "value": 17.47
                },
                {
                    "name": "WIND_BEARING",
                    "value": 6.27
                }
            ]
        },
        {
            "fromDateTime": "2025-05-15T07:00:00.000Z",
            "indexes": [
                {
                    "advice": "It couldn't be better ;)",
                    "color": "#6BC926",
                    "description": "Great air here today!",
                    "level": "VERY_LOW",
                    "name": "AIRLY_CAQI",
                    "value": 4.59
                }
            ],
            "standards": [
                {
                    "averaging": "24h",
                    "limit": 15.0,
                    "name": "WHO",
                    "percent": 18.34,
                    "pollutant": "PM25"
                },
                {
                    "averaging": "24h",
                    "limit": 45.0,
                    "name": "WHO",
                    "percent": 8.45,
                    "pollutant": "PM10"
                }
            ],
            "tillDateTime": "2025-05-15T08:00:00.000Z",
            "values": [
                {
                    "name": "PM1",
                    "value": 1.88
                },
                {
                    "name": "PM25",
                    "value": 2.75
                },
                {
                    "name": "PM10",
                    "value": 3.8
                },
                {
                    "name": "PRESSURE",
                    "value": 1006.95
                },
                {
                    "name": "HUMIDITY",
                    "value": 93.25
                },
                {
                    "name": "TEMPERATURE",
                    "value": 3.18
                },
                {
                    "name": "WIND_SPEED",
                    "value": 13.81
                },
                {
                    "name": "WIND_BEARING",
                    "value": 359.08
                }
            ]
        },
        {
            "fromDateTime": "2025-05-15T08:00:00.000Z",
            "indexes": [
                {
                    "advice": "Breathe deeply!",
                    "color": "#6BC926",
                    "description": "Great air here today!",
                    "level": "VERY_LOW",
                    "name": "AIRLY_CAQI",
                    "value": 7.95
                }
            ],
            "standards": [
                {
                    "averaging": "24h",
                    "limit": 15.0,
                    "name": "WHO",
                    "percent": 31.79,
                    "pollutant": "PM25"
                },
                {
                    "averaging": "24h",
                    "limit": 45.0,
                    "name": "WHO",
                    "percent": 14.89,
                    "pollutant": "PM10"
                }
            ],
            "tillDateTime": "2025-05-15T09:00:00.000Z",
            "values": [
                {
                    "name": "PM1",
                    "value": 3.12
                },
                {
                    "name": "PM25",
                    "value": 4.77
                },
                {
                    "name": "PM10",
                    "value": 6.7
                },
                {
                    "name": "PRESSURE",
                    "value": 1007.69
                },
                {
                    "name": "HUMIDITY",
                    "value": 90.94
                },
                {
                    "name": "TEMPERATURE",
                    "value": 3.69
                },
                {
                    "name": "WIND_SPEED",
                    "value": 11.14
                },
                {
                    "name": "WIND_BEARING",
                    "value": 340.44
                }
            ]
        },
        {
            "fromDateTime": "2025-05-15T09:00:00.000Z",
            "indexes": [
                {
                    "advice": "Breathe deep! The air is clean!",
                    "color": "#6BC926",
                    "description": "Great air here today!",
                    "level": "VERY_LOW",
                    "name": "AIRLY_CAQI",
                    "value": 5.65
                }
            ],
            "standards": [
                {
                    "averaging": "24h",
                    "limit": 15.0,
                    "name": "WHO",
                    "percent": 22.57,
                    "pollutant": "PM25"
                },
                {
                    "averaging": "24h",
                    "limit": 45.0,
                    "name": "WHO",
                    "percent": 10.52,
                    "pollutant": "PM10"
                }
            ],
            "tillDateTime": "2025-05-15T10:00:00.000Z",
            "values": [
                {
                    "name": "PM1",
                    "value": 2.27
                },
                {
                    "name": "PM25",
                    "value": 3.39
                },
                {
                    "name": "PM10",
                    "value": 4.74
                },
                {
                    "name": "PRESSURE",
                    "value": 1008.27
                },
                {
                    "name": "HUMIDITY",
                    "value": 86.31
                },
                {
                    "name": "TEMPERATURE",
                    "value": 4.91
                },
                {
                    "name": "WIND_SPEED",
                    "value": 9.98
                },
                {
                    "name": "WIND_BEARING",
                    "value": 326.17
                }
            ]
        },
        {
            "fromDateTime": "2025-05-15T10:00:00.000Z",
            "indexes": [
                {
                    "advice": "Perfect air for exercising! Go for it!",
                    "color": "#6BC926",
                    "description": "Great air here today!",
                    "level": "VERY_LOW",
                    "name": "AIRLY_CAQI",
                    "value": 6.45
                }
            ],
            "standards": [
                {
                    "averaging": "24h",
                    "limit": 15.0,
                    "name": "WHO",
                    "percent": 25.79,
                    "pollutant": "PM25"
                },
                {
                    "averaging": "24h",
                    "limit": 45.0,
                    "name": "WHO",
                    "percent": 11.69,
                    "pollutant": "PM10"
                }
            ],
            "tillDateTime": "2025-05-15T11:00:00.000Z",
            "values": [
                {
                    "name": "PM1",
                    "value": 2.7
                },
                {
                    "name": "PM25",
                    "value": 3.87
                },
                {
                    "name": "PM10",
                    "value": 5.26
                },
                {
                    "name": "PRESSURE",
                    "value": 1008.69
                },
                {
                    "name": "HUMIDITY",
                    "value": 80.5
                },
                {
                    "name": "TEMPERATURE",
                    "value": 6.39
                },
                {
                    "name": "WIND_SPEED",
                    "value": 9.73
                },
                {
                    "name": "WIND_BEARING",
                    "value": 319.0
                }
            ]
        },
        {
            "fromDateTime": "2025-05-15T11:00:00.000Z",
            "indexes": [
                {
                    "advice": "Zero dust - zero worries!",
                    "color": "#6BC926",
                    "description": "Great air here today!",
                    "level": "VERY_LOW",
                    "name": "AIRLY_CAQI",
                    "value": 10.71
                }
            ],
            "standards": [
                {
                    "averaging": "24h",
                    "limit": 15.0,
                    "name": "WHO",
                    "percent": 42.81,
                    "pollutant": "PM25"
                },
                {
                    "averaging": "24h",
                    "limit": 45.0,
                    "name": "WHO",
                    "percent": 19.99,
                    "pollutant": "PM10"
                }
            ],
            "tillDateTime": "2025-05-15T12:00:00.000Z",
            "values": [
                {
                    "name": "PM1",
                    "value": 4.12
                },
                {
                    "name": "PM25",
                    "value": 6.42
                },
                {
                    "name": "PM10",
                    "value": 8.99
                },
                {
                    "name": "PRESSURE",
                    "value": 1008.87
                },
                {
                    "name": "HUMIDITY",
                    "value": 74.82
                },
                {
                    "name": "TEMPERATURE",
                    "value": 7.7
                },
                {
                    "name": "WIND_SPEED",
                    "value": 10.77
                },
                {
                    "name": "WIND_BEARING",
                    "value": 319.0
                }
            ]
        },
        {
            "fromDateTime": "2025-05-15T12:00:00.000Z",
            "indexes": [
                {
                    "advice": "Breathe to fill your lungs!",
                    "color": "#6BC926",
                    "description": "Great air here today!",
                    "level": "VERY_LOW",
                    "name": "AIRLY_CAQI",
                    "value": 4.7
                }
            ],
            "standards": [
                {
                    "averaging": "24h",
                    "limit": 15.0,
                    "name": "WHO",
                    "percent": 18.78,
                    "pollutant": "PM25"
                },
                {
                    "averaging": "24h",
                    "limit": 45.0,
                    "name": "WHO",
                    "percent": 8.42,
                    "pollutant": "PM10"
                }
            ],
            "tillDateTime": "2025-05-15T13:00:00.000Z",
            "values": [
                {
                    "name": "PM1",
                    "value": 2.1
                },
                {
                    "name": "PM25",
                    "value": 2.82
                },
                {
                    "name": "PM10",
                    "value": 3.79
                },
                {
                    "name": "PRESSURE",
                    "value": 1008.83
                },
                {
                    "name": "HUMIDITY",
                    "value": 70.22
                },
                {
                    "name": "TEMPERATURE",
                    "value": 8.85
                },
                {
                    "name": "WIND_SPEED",
                    "value": 11.77
                },
                {
                    "name": "WIND_BEARING",
                    "value": 317.99
                }
            ]
        },
        {
            "fromDateTime": "2025-05-15T13:00:00.000Z",
            "indexes": [
                {
                    "advice": "It couldn't be better ;)",
                    "color": "#6BC926",
                    "description": "Great air here today!",
                    "level": "VERY_LOW",
                    "name": "AIRLY_CAQI",
                    "value": 4.96
                }
            ],
            "standards": [
                {
                    "averaging": "24h",
                    "limit": 15.0,
                    "name": "WHO",
                    "percent": 19.84,
                    "pollutant": "PM25"
                },
                {
                    "averaging": "24h",
                    "limit": 45.0,
                    "name": "WHO",
                    "percent": 8.94,
                    "pollutant": "PM10"
                }
            ],
            "tillDateTime": "2025-05-15T14:00:00.000Z",
            "values": [
                {
                    "name": "PM1",
                    "value": 2.09
                },
                {
                    "name": "PM25",
                    "value": 2.98
                },
                {
                    "name": "PM10",
                    "value": 4.02
                },
                {
                    "name": "PRESSURE",
                    "value": 1008.87
                },
                {
                    "name": "HUMIDITY",
                    "value": 67.78
                },
                {
                    "name": "TEMPERATURE",
                    "value": 9.31
                },
                {
                    "name": "WIND_SPEED",
                    "value": 12.03
                },
                {
                    "name": "WIND_BEARING",
                    "value": 316.31
                }
            ]
        },
        {
            "fromDateTime": "2025-05-15T14:00:00.000Z",
            "indexes": [
                {
                    "advice": "Zero dust - zero worries!",
                    "color": "#6BC926",
                    "description": "Great air here today!",
                    "level": "VERY_LOW",
                    "name": "AIRLY_CAQI",
                    "value": 3.58
                }
            ],
            "standards": [
                {
                    "averaging": "24h",
                    "limit": 15.0,
                    "name": "WHO",
                    "percent": 14.32,
                    "pollutant": "PM25"
                },
                {
                    "averaging": "24h",
                    "limit": 45.0,
                    "name": "WHO",
                    "percent": 6.4,
                    "pollutant": "PM10"
                }
            ],
            "tillDateTime": "2025-05-15T15:00:00.000Z",
            "values": [
                {
                    "name": "PM1",
                    "value": 1.52
                },
                {
                    "name": "PM25",
                    "value": 2.15
                },
                {
                    "name": "PM10",
                    "value": 2.88
                },
                {
                    "name": "PRESSURE",
                    "value": 1009.25
                },
                {
                    "name": "HUMIDITY",
                    "value": 64.92
                },
                {
                    "name": "TEMPERATURE",
                    "value": 9.32
                },
                {
                    "name": "WIND_SPEED",
                    "value": 12.46
                },
                {
                    "name": "WIND_BEARING",
                    "value": 312.34
                }
            ]
        },
        {
            "fromDateTime": "2025-05-15T15:00:00.000Z",
            "indexes": [
                {
                    "advice": "Breathe deeply!",
                    "color": "#6BC926",
                    "description": "Great air here today!",
                    "level": "VERY_LOW",
                    "name": "AIRLY_CAQI",
                    "value": 3.13
                }
            ],
            "standards": [
                {
                    "averaging": "24h",
                    "limit": 15.0,
                    "name": "WHO",
                    "percent": 12.48,
                    "pollutant": "PM25"
                },
                {
                    "averaging": "24h",
                    "limit": 45.0,
                    "name": "WHO",
                    "percent": 5.53,
                    "pollutant": "PM10"
                }
            ],
            "tillDateTime": "2025-05-15T16:00:00.000Z",
            "values": [
                {
                    "name": "PM1",
                    "value": 1.3
                },
                {
                    "name": "PM25",
                    "value": 1.87
                },
                {
                    "name": "PM10",
                    "value": 2.49
                },
                {
                    "name": "PRESSURE",
                    "value": 1009.28
                },
                {
                    "name": "HUMIDITY",
                    "value": 65.16
                },
                {
                    "name": "TEMPERATURE",
                    "value": 9.22
                },
                {
                    "name": "WIND_SPEED",
                    "value": 11.9
                },
                {
                    "name": "WIND_BEARING",
                    "value": 304.0
                }
            ]
        },
        {
            "fromDateTime": "2025-05-15T16:00:00.000Z",
            "indexes": [
                {
                    "advice": "The air is great!",
                    "color": "#6BC926",
                    "description": "Great air here today!",
                    "level": "VERY_LOW",
                    "name": "AIRLY_CAQI",
                    "value": 3.41
                }
            ],
            "standards": [
                {
                    "averaging": "24h",
                    "limit": 15.0,
                    "name": "WHO",
                    "percent": 13.63,
                    "pollutant": "PM25"
                },
                {
                    "averaging": "24h",
                    "limit": 45.0,
                    "name": "WHO",
                    "percent": 6.18,
                    "pollutant": "PM10"
                }
            ],
            "tillDateTime": "2025-05-15T17:00:00.000Z",
            "values": [
                {
                    "name": "PM1",
                    "value": 1.38
                },
                {
                    "name": "PM25",
                    "value": 2.04
                },
                {
                    "name": "PM10",
                    "value": 2.78
                },
                {
                    "name": "PRESSURE",
                    "value": 1009.73
                },
                {
                    "name": "HUMIDITY",
                    "value": 68.21
                },
                {
                    "name": "TEMPERATURE",
                    "value": 8.3
                },
                {
                    "name": "WIND_SPEED",
                    "value": 11.97
                },
                {
                    "name": "WIND_BEARING",
                    "value": 292.07
                }
            ]
        },
        {
            "fromDateTime": "2025-05-15T17:00:00.000Z",
            "indexes": [
                {
                    "advice": "Breathe as much as you can!",
                    "color": "#6BC926",
                    "description": "Great air here today!",
                    "level": "VERY_LOW",
                    "name": "AIRLY_CAQI",
                    "value": 6.71
                }
            ],
            "standards": [
                {
                    "averaging": "24h",
                    "limit": 15.0,
                    "name": "WHO",
                    "percent": 26.82,
                    "pollutant": "PM25"
                },
                {
                    "averaging": "24h",
                    "limit": 45.0,
                    "name": "WHO",
                    "percent": 12.37,
                    "pollutant": "PM10"
                }
            ],
            "tillDateTime": "2025-05-15T18:00:00.000Z",
            "values": [
                {
                    "name": "PM1",
                    "value": 2.79
                },
                {
                    "name": "PM25",
                    "value": 4.02
                },
                {
                    "name": "PM10",
                    "value": 5.57
                },
                {
                    "name": "PRESSURE",
                    "value": 1009.98
                },
                {
                    "name": "HUMIDITY",
                    "value": 72.25
                },
                {
                    "name": "TEMPERATURE",
                    "value": 7.53
                },
                {
                    "name": "WIND_SPEED",
                    "value": 10.66
                },
                {
                    "name": "WIND_BEARING",
                    "value": 287.93
                }
            ]
        },
        {
            "fromDateTime": "2025-05-15T18:00:00.000Z",
            "indexes": [
                {
                    "advice": "Green, green, green!",
                    "color": "#6BC926",
                    "description": "Great air here today!",
                    "level": "VERY_LOW",
                    "name": "AIRLY_CAQI",
                    "value": 8.63
                }
            ],
            "standards": [
                {
                    "averaging": "24h",
                    "limit": 15.0,
                    "name": "WHO",
                    "percent": 34.5,
                    "pollutant": "PM25"
                },
                {
                    "averaging": "24h",
                    "limit": 45.0,
                    "name": "WHO",
                    "percent": 16.2,
                    "pollutant": "PM10"
                }
            ],
            "tillDateTime": "2025-05-15T19:00:00.000Z",
            "values": [
                {
                    "name": "PM1",
                    "value": 3.36
                },
                {
                    "name": "PM25",
                    "value": 5.17
                },
                {
                    "name": "PM10",
                    "value": 7.29
                },
                {
                    "name": "PRESSURE",
                    "value": 1010.34
                },
                {
                    "name": "HUMIDITY",
                    "value": 80.88
                },
                {
                    "name": "TEMPERATURE",
                    "value": 6.24
                },
                {
                    "name": "WIND_SPEED",
                    "value": 9.7
                },
                {
                    "name": "WIND_BEARING",
                    "value": 289.72
                }
            ]
        },
        {
            "fromDateTime": "2025-05-15T19:00:00.000Z",
            "indexes": [
                {
                    "advice": "Green equals clean!",
                    "color": "#6BC926",
                    "description": "Great air here today!",
                    "level": "VERY_LOW",
                    "name": "AIRLY_CAQI",
                    "value": 11.45
                }
            ],
            "standards": [
                {
                    "averaging": "24h",
                    "limit": 15.0,
                    "name": "WHO",
                    "percent": 45.78,
                    "pollutant": "PM25"
                },
                {
                    "averaging": "24h",
                    "limit": 45.0,
                    "name": "WHO",
                    "percent": 21.39,
                    "pollutant": "PM10"
                }
            ],
            "tillDateTime": "2025-05-15T20:00:00.000Z",
            "values": [
                {
                    "name": "PM1",
                    "value": 4.48
                },
                {
                    "name": "PM25",
                    "value": 6.87
                },
                {
                    "name": "PM10",
                    "value": 9.62
                },
                {
                    "name": "PRESSURE",
                    "value": 1010.8
                },
                {
                    "name": "HUMIDITY",
                    "value": 87.25
                },
                {
                    "name": "TEMPERATURE",
                    "value": 5.28
                },
                {
                    "name": "WIND_SPEED",
                    "value": 9.84
                },
                {
                    "name": "WIND_BEARING",
                    "value": 289.63
                }
            ]
        },
        {
            "fromDateTime": "2025-05-15T20:00:00.000Z",
            "indexes": [
                {
                    "advice": "Perfect air for exercising! Go for it!",
                    "color": "#6BC926",
                    "description": "Great air here today!",
                    "level": "VERY_LOW",
                    "name": "AIRLY_CAQI",
                    "value": 13.91
                }
            ],
            "standards": [
                {
                    "averaging": "24h",
                    "limit": 15.0,
                    "name": "WHO",
                    "percent": 55.63,
                    "pollutant": "PM25"
                },
                {
                    "averaging": "24h",
                    "limit": 45.0,
                    "name": "WHO",
                    "percent": 25.24,
                    "pollutant": "PM10"
                }
            ],
            "tillDateTime": "2025-05-15T21:00:00.000Z",
            "values": [
                {
                    "name": "PM1",
                    "value": 5.7
                },
                {
                    "name": "PM25",
                    "value": 8.35
                },
                {
                    "name": "PM10",
                    "value": 11.36
                },
                {
                    "name": "PRESSURE",
                    "value": 1011.02
                },
                {
                    "name": "HUMIDITY",
                    "value": 89.5
                },
                {
                    "name": "TEMPERATURE",
                    "value": 4.8
                },
                {
                    "name": "WIND_SPEED",
                    "value": 9.86
                },
                {
                    "name": "WIND_BEARING",
                    "value": 282.47
                }
            ]
        },
        {
            "fromDateTime": "2025-05-15T21:00:00.000Z",
            "indexes": [
                {
                    "advice": "Catch your breath!",
                    "color": "#6BC926",
                    "description": "Great air here today!",
                    "level": "VERY_LOW",
                    "name": "AIRLY_CAQI",
                    "value": 13.41
                }
            ],
            "standards": [
                {
                    "averaging": "24h",
                    "limit": 15.0,
                    "name": "WHO",
                    "percent": 53.61,
                    "pollutant": "PM25"
                },
                {
                    "averaging": "24h",
                    "limit": 45.0,
                    "name": "WHO",
                    "percent": 23.92,
                    "pollutant": "PM10"
                }
            ],
            "tillDateTime": "2025-05-15T22:00:00.000Z",
            "values": [
                {
                    "name": "PM1",
                    "value": 5.49
                },
                {
                    "name": "PM25",
                    "value": 8.04
                },
                {
                    "name": "PM10",
                    "value": 10.76
                },
                {
                    "name": "PRESSURE",
                    "value": 1011.4
                },
                {
                    "name": "HUMIDITY",
                    "value": 91.38
                },
                {
                    "name": "TEMPERATURE",
                    "value": 4.08
                },
                {
                    "name": "WIND_SPEED",
                    "value": 10.37
                },
                {
                    "name": "WIND_BEARING",
                    "value": 281.0
                }
            ]
        }
    ]
}